obo_parser/__init__.py
obo_parser/bin.py
obo_parser/parser.py
obo_parser/utils.py
obo_parser/version.json
obo_parser-1.0.3.dist-info/METADATA
obo_parser-1.0.3.dist-info/WHEEL
obo_parser-1.0.3.dist-info/entry_points.txt
obo_parser-1.0.3.dist-info/top_level.txt
obo_parser-1.0.3.dist-info/RECORD
