Metadata-Version: 2.1
Name: obo_parser
Version: 1.0.3
Summary: A Python library for parsing OBO (Open Biological and Biomedical Ontologies) files.
Home-page: https://github.com/suqingdong/obo_parser
Author: suqingdong
Author-email: suqingdong1114@gmail.com
License: MIT License
Classifier: Development Status :: 5 - Production/Stable
Classifier: Operating System :: OS Independent
Classifier: Intended Audience :: Developers
Classifier: License :: OSI Approved :: MIT License
Classifier: Programming Language :: Python
Classifier: Programming Language :: Python :: 3
Classifier: Programming Language :: Python :: 3.9
Classifier: Programming Language :: Python :: 3.10
Classifier: Programming Language :: Python :: 3.11
Classifier: Programming Language :: Python :: 3.12
Classifier: Topic :: Software Development :: Libraries
Requires-Dist: click
Requires-Dist: requests
